Metadata-Version: 1.0
Name: ConcurrentLogHandler
Version: 0.8.5
Summary:  Concurrent logging handler (drop-in replacement for RotatingFileHandler)
Home-page: http://launchpad.net/python-concurrent-log-handler
Author: Lowell Alleman
Author-email: lowell87@gmail.com
License: http://www.apache.org/licenses/LICENSE-2.0
Keywords: logging,windows,linux,unix,rotate,portalocker
Platform: nt
Platform: posix
Classifier: Development Status :: 5 - Production/Stable
Classifier: Topic :: System :: Logging
Classifier: Operating System :: POSIX
Classifier: Operating System :: Microsoft :: Windows
Classifier: Programming Language :: Python
Classifier: Programming Language :: Python :: 2.4
Classifier: Programming Language :: Python :: 2.5
Classifier: Programming Language :: Python :: 2.6
Classifier: Programming Language :: Python :: 2.7
Classifier: Programming Language :: Python :: 3
Classifier: Topic :: Software Development :: Libraries :: Python Modules
Classifier: License :: OSI Approved :: Apache Software License
